game_base/__init__.py
game_base/base/__init__.py
game_base/base/constant.py
game_base/base/send_message.py
game_base/base/server.py
game_base/base/game/__init__.py
game_base/base/game/base/__init__.py
game_base/base/game/base/command/__init__.py
game_base/base/game/base/command/action_cmd.py
game_base/base/game/base/command/chat_cmd.py
game_base/base/game/base/command/create_room_cmd.py
game_base/base/game/base/command/create_union_room_cmd.py
game_base/base/game/base/command/delete_union_room_cmd.py
game_base/base/game/base/command/dissolved_room_cmd.py
game_base/base/game/base/command/enter_room_cmd.py
game_base/base/game/base/command/exit_room_cmd.py
game_base/base/game/base/command/game_flow_cmd.py
game_base/base/game/base/command/gps_cmd.py
game_base/base/game/base/command/online_cmd.py
game_base/base/game/base/command/ready_cmd.py
game_base/base/game/base/command/rebate_cmd.py
game_base/base/game/base/command/reconnect_cmd.py
game_base/base/game/base/command/record_cmd.py
game_base/base/game/base/command/replay_dissolved_room_cmd.py
game_base/base/game/base/command/room_over_cmd.py
game_base/base/game/base/command/room_record_cmd.py
game_base/base/game/base/command/room_review_cmd.py
game_base/base/game/base/command/room_win_lose_cmd.py
game_base/base/game/base/command/seat_down_cmd.py
game_base/base/game/base/command/stand_up_cmd.py
game_base/base/game/base/command/take_score_cmd.py
game_base/base/game/base/command/update_union_room_cmd.py
game_base/base/game/base/command/voice_cmd.py
game_base/base/game/base/command/watch_list_cmd.py
game_base/base/game/base/handle/__init__.py
game_base/base/game/base/handle/timeout_handle.py
game_base/base/game/base/logic/__init__.py
game_base/base/game/base/logic/mahjong_utils.py
game_base/base/game/base/logic/poker_card_utils.py
game_base/base/game/base/timeout/__init__.py
game_base/base/game/base/timeout/dissolved_timeout.py
game_base/base/game/base/timeout/leave_seat_timeout.py
game_base-0.0.3.dist-info/METADATA
game_base-0.0.3.dist-info/WHEEL
game_base-0.0.3.dist-info/top_level.txt
game_base-0.0.3.dist-info/RECORD
